jsondataclass/__init__.py
jsondataclass/jsondataclass.py
betterjsdc-1.0.0.dist-info/LICENSE
betterjsdc-1.0.0.dist-info/METADATA
betterjsdc-1.0.0.dist-info/WHEEL
betterjsdc-1.0.0.dist-info/top_level.txt
betterjsdc-1.0.0.dist-info/RECORD
